pyBaiduPan/__init__.py
pyBaiduPan/__main__.py
pyBaiduPan/bdpan.py
pyBaiduPan/config.py
pyBaiduPan/exceptions.py
pyBaiduPan/login.py
pyBaiduPan-0.2.0.dist-info/LICENSE
pyBaiduPan-0.2.0.dist-info/METADATA
pyBaiduPan-0.2.0.dist-info/WHEEL
pyBaiduPan-0.2.0.dist-info/entry_points.txt
pyBaiduPan-0.2.0.dist-info/top_level.txt
pyBaiduPan-0.2.0.dist-info/RECORD
