Metadata-Version: 2.1
Name: pyBaiduPan
Version: 0.2.0
Summary: A python client for Baidu Pan
Home-page: https://github.com/AlphaCat00/PyBaiduPan
Author: AlphaCat
Author-email: 00.alpha.cat@gmail.com
License: UNKNOWN
Keywords: baidu pcs,baidu yun,baidu pan,baidu netdisk,baidu cloud storage,baidu personal cloud storage
Platform: UNKNOWN
Classifier: Programming Language :: Python :: 3
Classifier: License :: OSI Approved :: MIT License
Classifier: Operating System :: OS Independent
Requires-Python: >=3.6
Requires-Dist: Flask (>=1.0)
Requires-Dist: requests (>=2.22.0)
